wwpy/__init__.py
wwpy/__main__.py
wwpy/version.py
wwpy/version.txt
wwpy/git_hooks/post_checkout.py
wwpy/git_hooks/pre_commit.py
wwpy/tests/test_version.py
wwpy-0.22.dist-info/METADATA
wwpy-0.22.dist-info/WHEEL
wwpy-0.22.dist-info/top_level.txt
wwpy-0.22.dist-info/RECORD
