Metadata-Version: 2.1
Name: wwpy
Version: 0.22
Summary: World Wide Python
License: BSD 3-Clause License
Classifier: Programming Language :: Python :: 3
Requires-Python: >=3.10
Requires-Dist: flake8 (>=6.0.0)
Requires-Dist: pytest (>=7.2.0)
